pychemstation/__init__.py
pychemstation/analysis/__init__.py
pychemstation/analysis/base_spectrum.py
pychemstation/analysis/chromatogram.py
pychemstation/analysis/process_report.py
pychemstation/control/README.md
pychemstation/control/__init__.py
pychemstation/control/hplc.py
pychemstation/control/controllers/README.md
pychemstation/control/controllers/__init__.py
pychemstation/control/controllers/comm.py
pychemstation/control/controllers/data_aq/__init__.py
pychemstation/control/controllers/data_aq/method.py
pychemstation/control/controllers/data_aq/sequence.py
pychemstation/control/controllers/devices/__init__.py
pychemstation/control/controllers/devices/column.py
pychemstation/control/controllers/devices/dad.py
pychemstation/control/controllers/devices/injector.py
pychemstation/control/controllers/devices/pump.py
pychemstation/control/controllers/devices/sample_info.py
pychemstation/generated/__init__.py
pychemstation/generated/dad_method.py
pychemstation/generated/pump_method.py
pychemstation/utils/__init__.py
pychemstation/utils/device_types.py
pychemstation/utils/injector_types.py
pychemstation/utils/macro.py
pychemstation/utils/method_types.py
pychemstation/utils/num_utils.py
pychemstation/utils/parsing.py
pychemstation/utils/sequence_types.py
pychemstation/utils/spec_utils.py
pychemstation/utils/table_types.py
pychemstation/utils/tray_types.py
pychemstation/utils/abc_tables/__init__.py
pychemstation/utils/abc_tables/abc_comm.py
pychemstation/utils/abc_tables/device.py
pychemstation/utils/abc_tables/run.py
pychemstation/utils/abc_tables/table.py
pychemstation/utils/mocking/__init__.py
pychemstation/utils/mocking/mock_comm.py
pychemstation/utils/mocking/mock_hplc.py
pychemstation-0.10.13.dist-info/METADATA
pychemstation-0.10.13.dist-info/WHEEL
pychemstation-0.10.13.dist-info/licenses/LICENSE
pychemstation-0.10.13.dist-info/RECORD
