Metadata-Version: 2.4
Name: pychemstation
Version: 0.10.0
Summary: Library to interact with Chemstation software, primarily used in Hein lagit branch -mb
Home-page: https://gitlab.com/heingroup/device-api/pychemstation
Author: Lucy Hao
Author-email: lucyhao <hao.lucyy@gmail.com>
Requires-Python: >=3.10
License-File: LICENSE
Requires-Dist: aghplctools>=4.8.8
Requires-Dist: coverage>=7.6.1
Requires-Dist: matplotlib>=3.7.5
Requires-Dist: pandas>=2.0.3
Requires-Dist: pdoc>=14.7.0
Requires-Dist: polling>=0.3.2
Requires-Dist: pytest>=7.3.5
Requires-Dist: rainbow-api>=1.0.10
Requires-Dist: result>=0.17.0
Requires-Dist: scipy>=1.10.1
Requires-Dist: seabreeze>=2.9.2
Requires-Dist: setuptools>=75.3.2
Requires-Dist: twine>=6.1.0
Requires-Dist: xsdata>=24.9
Dynamic: author
Dynamic: home-page
Dynamic: license-file
